{"outdoor_pine_round_table":{"id":"outdoor_pine_round_table","name":"Outdoor Pine Round Table","load":85,"energy":30,"ratio":0.35294117647058826,"type":"interior","recipe":[{"id":"Pine Wood","amount":4}]},"wooden_restaurant_signboard":{"id":"wooden_restaurant_signboard","name":"Wooden Restaurant Signboard","load":85,"energy":30,"ratio":0.35294117647058826,"type":"interior","recipe":[{"id":"Fir Wood","amount":4},{"id":"Blue Dye","amount":4}]},"pine_dining_chair":{"id":"pine_dining_chair","name":"Pine Dining Chair","load":85,"energy":30,"ratio":0.35294117647058826,"type":"interior","recipe":[{"id":"Pine Wood","amount":4}]},"well-worn_buckler":{"id":"well-worn_buckler","name":"Well-Worn Buckler","load":85,"energy":30,"ratio":0.35294117647058826,"type":"interior","recipe":[{"id":"Fir Wood","amount":4},{"id":"Iron Chunk","amount":4}]},"well-worn_shield":{"id":"well-worn_shield","name":"Well-Worn Shield","load":85,"energy":30,"ratio":0.35294117647058826,"type":"interior","recipe":[{"id":"Fir Wood","amount":4},{"id":"Iron Chunk","amount":4}]},"well-worn_sword":{"id":"well-worn_sword","name":"Well-Worn Sword","load":85,"energy":30,"ratio":0.35294117647058826,"type":"interior","recipe":[{"id":"Fir Wood","amount":4},{"id":"Iron Chunk","amount":4}]},"mounted_record_board":{"id":"mounted_record_board","name":"Mounted Record Board","load":85,"energy":30,"ratio":0.35294117647058826,"type":"interior","recipe":[{"id":"Fir Wood","amount":4},{"id":"Blue Dye","amount":4}]},"mounted_noticeboard":{"id":"mounted_noticeboard","name":"Mounted Noticeboard","load":85,"energy":30,"ratio":0.35294117647058826,"type":"interior","recipe":[{"id":"Fir Wood","amount":4},{"id":"Blue Dye","amount":4}]},"straw_hut":{"id":"straw_hut","name":"Straw Hut","load":125,"energy":30,"ratio":0.24,"type":"exterior","recipe":[{"id":"Fir Wood","amount":8}]},"straw_depot":{"id":"straw_depot","name":"Straw Depot","load":110,"energy":30,"ratio":0.2727272727272727,"type":"exterior","recipe":[{"id":"Fir Wood","amount":8}]},"straw_shed":{"id":"straw_shed","name":"Straw Shed","load":35,"energy":30,"ratio":0.8571428571428571,"type":"exterior","recipe":[{"id":"Fir Wood","amount":8}]},"hilichurl_straw_hut":{"id":"hilichurl_straw_hut","name":"Hilichurl Straw Hut","load":95,"energy":30,"ratio":0.3157894736842105,"type":"exterior","recipe":[{"id":"Birch Wood","amount":4}]},"doorless_pine_cupboard":{"id":"doorless_pine_cupboard","name":"Doorless Pine Cupboard","load":35,"energy":30,"ratio":0.8571428571428571,"type":"exterior","recipe":[{"id":"Pine Wood","amount":6},{"id":"Fabric","amount":2}]},"long_pine_table":{"id":"long_pine_table","name":"Long Pine Table","load":35,"energy":30,"ratio":0.8571428571428571,"type":"exterior","recipe":[{"id":"Pine Wood","amount":8}]},"fir_shelves":{"id":"fir_shelves","name":"Fir Shelves","load":65,"energy":30,"ratio":0.46153846153846156,"type":"exterior","recipe":[{"id":"Fir Wood","amount":4}]},"fir_weapon_rack":{"id":"fir_weapon_rack","name":"Fir Weapon Rack","load":35,"energy":30,"ratio":0.8571428571428571,"type":"exterior","recipe":[{"id":"Fir Wood","amount":4}]},"messy_pile_of_fir_crates":{"id":"messy_pile_of_fir_crates","name":"Messy Pile of Fir Crates","load":40,"energy":30,"ratio":0.75,"type":"exterior","recipe":[{"id":"Fir Wood","amount":4}]},"neat_stack_of_fir_kegs":{"id":"neat_stack_of_fir_kegs","name":"Neat Stack of Fir Kegs","load":35,"energy":30,"ratio":0.8571428571428571,"type":"exterior","recipe":[{"id":"Fir Wood","amount":4}]},"simple_cargo_cart":{"id":"simple_cargo_cart","name":"Simple Cargo Cart","load":65,"energy":30,"ratio":0.46153846153846156,"type":"exterior","recipe":[{"id":"Fir Wood","amount":4}]},"heavy_hay_bale":{"id":"heavy_hay_bale","name":"Heavy Hay Bale","load":35,"energy":30,"ratio":0.8571428571428571,"type":"exterior","recipe":[{"id":"Fir Wood","amount":4}]},"storage_sack_buzz-off_bag":{"id":"storage_sack_buzz-off_bag","name":"Storage Sack: Buzz-Off Bag","load":35,"energy":30,"ratio":0.8571428571428571,"type":"exterior","recipe":[{"id":"Fabric","amount":4}]},"old_well":{"id":"old_well","name":"Old Well","load":95,"energy":30,"ratio":0.3157894736842105,"type":"exterior","recipe":[{"id":"White Iron Chunk","amount":4}]},"hardened_glazed_vase":{"id":"hardened_glazed_vase","name":"Hardened Glazed Vase","load":35,"energy":30,"ratio":0.8571428571428571,"type":"exterior","recipe":[{"id":"Iron Chunk","amount":4}]},"weathered_bamboo_fence":{"id":"weathered_bamboo_fence","name":"Weathered Bamboo Fence","load":35,"energy":30,"ratio":0.8571428571428571,"type":"exterior","recipe":[{"id":"Bamboo Segment","amount":4}]},"sturdy_pine_fence":{"id":"sturdy_pine_fence","name":"Sturdy Pine Fence","load":35,"energy":30,"ratio":0.8571428571428571,"type":"exterior","recipe":[{"id":"Pine Wood","amount":4}]},"wooden_hilichurl_fence":{"id":"wooden_hilichurl_fence","name":"Wooden Hilichurl Fence","load":65,"energy":30,"ratio":0.46153846153846156,"type":"exterior","recipe":[{"id":"Fir Wood","amount":4}]},"hilichurl_totem_fence":{"id":"hilichurl_totem_fence","name":"Hilichurl Totem Fence","load":65,"energy":30,"ratio":0.46153846153846156,"type":"exterior","recipe":[{"id":"Fir Wood","amount":4}]},"deadwood_road_sign":{"id":"deadwood_road_sign","name":"Deadwood Road Sign","load":65,"energy":30,"ratio":0.46153846153846156,"type":"exterior","recipe":[{"id":"Fir Wood","amount":4}]},"smooth_wooden_bench":{"id":"smooth_wooden_bench","name":"Smooth Wooden Bench","load":35,"energy":30,"ratio":0.8571428571428571,"type":"exterior","recipe":[{"id":"Fir Wood","amount":4}]},"smooth_stone_bench":{"id":"smooth_stone_bench","name":"Smooth Stone Bench","load":35,"energy":30,"ratio":0.8571428571428571,"type":"exterior","recipe":[{"id":"White Iron Chunk","amount":4}]},"pine_street_light":{"id":"pine_street_light","name":"Pine Street Light","load":85,"energy":30,"ratio":0.35294117647058826,"type":"exterior","recipe":[{"id":"Pine Wood","amount":4}]},"overgrown_wildvest":{"id":"overgrown_wildvest","name":"Overgrown Wildvest","load":50,"energy":10,"ratio":0.2,"type":"exterior","cost":40},"hazel_wildvest":{"id":"hazel_wildvest","name":"Hazel Wildvest","load":50,"energy":10,"ratio":0.2,"type":"exterior","cost":40},"wine-red_wildvest":{"id":"wine-red_wildvest","name":"Wine-Red Wildvest","load":50,"energy":10,"ratio":0.2,"type":"exterior","cost":40},"profuse_smokeleaf":{"id":"profuse_smokeleaf","name":"Profuse Smokeleaf","load":50,"energy":10,"ratio":0.2,"type":"exterior","cost":40},"vivacious_smokeleaf":{"id":"vivacious_smokeleaf","name":"Vivacious Smokeleaf","load":50,"energy":10,"ratio":0.2,"type":"exterior","cost":40},"profuse_lacquerleaf":{"id":"profuse_lacquerleaf","name":"Profuse Lacquerleaf","load":50,"energy":10,"ratio":0.2,"type":"exterior","cost":40},"vivacious_lacquerleaf":{"id":"vivacious_lacquerleaf","name":"Vivacious Lacquerleaf","load":50,"energy":10,"ratio":0.2,"type":"exterior","cost":40},"profuse_awlking":{"id":"profuse_awlking","name":"Profuse Awlking","load":50,"energy":10,"ratio":0.2,"type":"exterior","cost":40},"vivacious_awlking":{"id":"vivacious_awlking","name":"Vivacious Awlking","load":50,"energy":10,"ratio":0.2,"type":"exterior","cost":40},"luscious_bloom":{"id":"luscious_bloom","name":"Luscious Bloom","load":50,"energy":10,"ratio":0.2,"type":"exterior","cost":40},"verdant_bloom":{"id":"verdant_bloom","name":"Verdant Bloom","load":50,"energy":10,"ratio":0.2,"type":"exterior","cost":40},"meadow_bloom":{"id":"meadow_bloom","name":"Meadow Bloom","load":50,"energy":10,"ratio":0.2,"type":"exterior","cost":40},"gemini_verdance":{"id":"gemini_verdance","name":"Gemini Verdance","load":50,"energy":10,"ratio":0.2,"type":"exterior","cost":40},"gemini_jasmine":{"id":"gemini_jasmine","name":"Gemini Jasmine","load":50,"energy":10,"ratio":0.2,"type":"exterior","cost":40},"jade-eyed_cat":{"id":"jade-eyed_cat","name":"Jade-Eyed Cat","load":500,"energy":100,"ratio":0.2,"type":"","recipe":[{"id":"Iron Chunk","amount":30}]},"northland_hound":{"id":"northland_hound","name":"Northland Hound","load":500,"energy":100,"ratio":0.2,"type":"","recipe":[{"id":"Iron Chunk","amount":30}]},"forest_boar":{"id":"forest_boar","name":"Forest Boar","load":500,"energy":100,"ratio":0.2,"type":"","recipe":[{"id":"Iron Chunk","amount":30}]},"azure_crane":{"id":"azure_crane","name":"Azure Crane","load":500,"energy":100,"ratio":0.2,"type":"","recipe":[{"id":"Iron Chunk","amount":30}]},"forest-patrol_hound":{"id":"forest-patrol_hound","name":"Forest-Patrol Hound","load":500,"energy":100,"ratio":0.2,"type":""},"shiba":{"id":"shiba","name":"Shiba","load":500,"energy":100,"ratio":0.2,"type":""},"black-back_hound":{"id":"black-back_hound","name":"Black-Back Hound","load":500,"energy":100,"ratio":0.2,"type":""},"northland_cat":{"id":"northland_cat","name":"Northland Cat","load":500,"energy":100,"ratio":0.2,"type":""},"tiger-striped_cat":{"id":"tiger-striped_cat","name":"Tiger-Striped Cat","load":500,"energy":100,"ratio":0.2,"type":""},"sheriff_cat":{"id":"sheriff_cat","name":"Sheriff Cat","load":500,"energy":100,"ratio":0.2,"type":""},"two-tier_candle_chandelier":{"id":"two-tier_candle_chandelier","name":"Two-Tier Candle Chandelier","load":305,"energy":60,"ratio":0.19672131147540983,"type":"interior","recipe":[{"id":"Birch Wood","amount":4},{"id":"Iron Chunk","amount":8}]},"eight-sided_lantern_lucky_day":{"id":"eight-sided_lantern_lucky_day","name":"Eight-Sided Lantern: Lucky Day","load":220,"energy":60,"ratio":0.2727272727272727,"type":"interior","recipe":[{"id":"Sandbearer Wood","amount":4},{"id":"Fabric","amount":4},{"id":"Red Dye","amount":4}]},"six-sided_lantern_harmony_in_friendship":{"id":"six-sided_lantern_harmony_in_friendship","name":"Six-Sided Lantern: Harmony in Friendship","load":220,"energy":60,"ratio":0.2727272727272727,"type":"interior","recipe":[{"id":"Sandbearer Wood","amount":8},{"id":"Fabric","amount":4}]},"night_of_the_party_pumpkins":{"id":"night_of_the_party_pumpkins","name":"\"Night of the Party Pumpkins\"","load":305,"energy":60,"ratio":0.19672131147540983,"type":"interior","recipe":[{"id":"Birch Wood","amount":4},{"id":"Fabric","amount":4},{"id":"Yellow Dye","amount":4}]},"sub-space_boulder_craggy_canopy":{"id":"sub-space_boulder_craggy_canopy","name":"Sub-Space Boulder: Craggy Canopy","load":50,"energy":20,"ratio":0.4,"type":"exterior","recipe":[{"id":"Pine Wood","amount":20}]},"sub-space_boulder_rocky_bulwark":{"id":"sub-space_boulder_rocky_bulwark","name":"Sub-Space Boulder: Rocky Bulwark","load":50,"energy":20,"ratio":0.4,"type":"exterior","recipe":[{"id":"Pine Wood","amount":20}]},"sub-space_boulder_verdant_peak":{"id":"sub-space_boulder_verdant_peak","name":"Sub-Space Boulder: Verdant Peak","load":50,"energy":20,"ratio":0.4,"type":"exterior","recipe":[{"id":"Pine Wood","amount":20}]},"sub-space_boulder_slumbering_stratus":{"id":"sub-space_boulder_slumbering_stratus","name":"Sub-Space Boulder: Slumbering Stratus","load":50,"energy":20,"ratio":0.4,"type":"exterior","recipe":[{"id":"Pine Wood","amount":20}]},"sub-space_boulder_palace_steps":{"id":"sub-space_boulder_palace_steps","name":"Sub-Space Boulder: Palace Steps","load":50,"energy":20,"ratio":0.4,"type":"exterior","recipe":[{"id":"Pine Wood","amount":20}]},"sub-space_boulder_refined_beauty":{"id":"sub-space_boulder_refined_beauty","name":"Sub-Space Boulder: Refined Beauty","load":50,"energy":20,"ratio":0.4,"type":"exterior","recipe":[{"id":"Pine Wood","amount":20}]},"sturdy_library_table":{"id":"sturdy_library_table","name":"Sturdy Library Table","load":169,"energy":60,"ratio":0.35502958579881655,"type":"interior","recipe":[{"id":"Cuihua Wood","amount":12}]},"favonius_office_table":{"id":"favonius_office_table","name":"Favonius Office Table","load":254,"energy":60,"ratio":0.23622047244094488,"type":"interior","recipe":[{"id":"Cuihua Wood","amount":12}]},"favonius_conference_table":{"id":"favonius_conference_table","name":"Favonius Conference Table","load":254,"energy":60,"ratio":0.23622047244094488,"type":"interior","recipe":[{"id":"Cuihua Wood","amount":12}]},"northern_birch_folding_counter":{"id":"northern_birch_folding_counter","name":"Northern Birch Folding Counter","load":85,"energy":60,"ratio":0.7058823529411765,"type":"interior","recipe":[{"id":"Birch Wood","amount":12}]},"portable_stove":{"id":"portable_stove","name":"Portable Stove","load":558,"energy":60,"ratio":0.10752688172043011,"type":"interior","recipe":[{"id":"Iron Chunk","amount":12}]},"long_table_with_tablecloth":{"id":"long_table_with_tablecloth","name":"Long Table With Tablecloth","load":169,"energy":60,"ratio":0.35502958579881655,"type":"interior","recipe":[{"id":"Pine Wood","amount":8},{"id":"Fabric","amount":4}]},"intricately_carved_calligraphy_table":{"id":"intricately_carved_calligraphy_table","name":"Intricately Carved Calligraphy Table","load":85,"energy":60,"ratio":0.7058823529411765,"type":"interior","recipe":[{"id":"Fragrant Cedar Wood","amount":12}]},"square_pine_tea_table":{"id":"square_pine_tea_table","name":"Square Pine Tea Table","load":85,"energy":60,"ratio":0.7058823529411765,"type":"interior","recipe":[{"id":"Pine Wood","amount":8},{"id":"Yellow Dye","amount":2},{"id":"Red Dye","amount":2}]},"pine_reception_counter":{"id":"pine_reception_counter","name":"Pine Reception Counter","load":101,"energy":60,"ratio":0.594059405940594,"type":"interior","recipe":[{"id":"Pine Wood","amount":12}]},"red_cedar_round_table":{"id":"red_cedar_round_table","name":"Red Cedar Round Table","load":85,"energy":60,"ratio":0.7058823529411765,"type":"interior","recipe":[{"id":"Fragrant Cedar Wood","amount":8},{"id":"Red Dye","amount":4}]},"northern_stone_hearth":{"id":"northern_stone_hearth","name":"Northern Stone Hearth","load":727,"energy":60,"ratio":0.08253094910591471,"type":"interior","recipe":[{"id":"White Iron Chunk","amount":12}]},"classical_lyre_tenor_of_the_wind":{"id":"classical_lyre_tenor_of_the_wind","name":"Classical Lyre: Tenor of the Wind","load":85,"energy":60,"ratio":0.7058823529411765,"type":"interior","recipe":[{"id":"Cuihua Wood","amount":12}]},"clear_blue_afternoon":{"id":"clear_blue_afternoon","name":"\"Clear Blue Afternoon\"","load":85,"energy":60,"ratio":0.7058823529411765,"type":"interior","recipe":[{"id":"Cuihua Wood","amount":8},{"id":"Blue Dye","amount":4}]},"unwavering_determination":{"id":"unwavering_determination","name":"\"Unwavering Determination\"","load":169,"energy":60,"ratio":0.35502958579881655,"type":"interior","recipe":[{"id":"Birch Wood","amount":8},{"id":"Blue Dye","amount":4}]},"pine-backed_tea_chair":{"id":"pine-backed_tea_chair","name":"Pine-Backed Tea Chair","load":85,"energy":60,"ratio":0.7058823529411765,"type":"interior","recipe":[{"id":"Pine Wood","amount":8},{"id":"Red Dye","amount":4}]},"red_pine_wood_round_stool":{"id":"red_pine_wood_round_stool","name":"Red Pine Wood Round Stool","load":85,"energy":60,"ratio":0.7058823529411765,"type":"interior","recipe":[{"id":"Pine Wood","amount":8},{"id":"Red Dye","amount":4}]},"bright_vase-shaped_sconce":{"id":"bright_vase-shaped_sconce","name":"Bright Vase-Shaped Sconce","load":169,"energy":60,"ratio":0.35502958579881655,"type":"interior","recipe":[{"id":"Iron Chunk","amount":8}]},"trusty_portable_lamp":{"id":"trusty_portable_lamp","name":"Trusty Portable Lamp","load":85,"energy":60,"ratio":0.7058823529411765,"type":"interior","recipe":[{"id":"Iron Chunk","amount":8}]},"liuli_pavilion_sandbearer_floor_lamp":{"id":"liuli_pavilion_sandbearer_floor_lamp","name":"Liuli Pavilion Sandbearer Floor Lamp","load":220,"energy":60,"ratio":0.2727272727272727,"type":"interior","recipe":[{"id":"Sandbearer Wood","amount":4},{"id":"Fabric","amount":4},{"id":"Red Dye","amount":4}]},"tianyuan_lantern_fragrant_brilliance":{"id":"tianyuan_lantern_fragrant_brilliance","name":"Tianyuan Lantern: Fragrant Brilliance","load":220,"energy":60,"ratio":0.2727272727272727,"type":"interior","recipe":[{"id":"Sandbearer Wood","amount":4},{"id":"Fabric","amount":4},{"id":"Red Dye","amount":4}]},"sturdy_birch_vanity":{"id":"sturdy_birch_vanity","name":"Sturdy Birch Vanity","load":85,"energy":60,"ratio":0.7058823529411765,"type":"interior","recipe":[{"id":"Birch Wood","amount":12}]},"open-top_fir_shelf":{"id":"open-top_fir_shelf","name":"Open-Top Fir Shelf","load":254,"energy":60,"ratio":0.23622047244094488,"type":"interior","recipe":[{"id":"Fir Wood","amount":12}]},"fir_case_shelf_combination":{"id":"fir_case_shelf_combination","name":"Fir Case Shelf Combination","load":338,"energy":60,"ratio":0.17751479289940827,"type":"interior","recipe":[{"id":"Fir Wood","amount":12}]},"classic_fir_cabinet":{"id":"classic_fir_cabinet","name":"Classic Fir Cabinet","load":85,"energy":60,"ratio":0.7058823529411765,"type":"interior","recipe":[{"id":"Fir Wood","amount":12}]},"red_cedar_scroll_shelf":{"id":"red_cedar_scroll_shelf","name":"Red Cedar Scroll Shelf","load":196,"energy":60,"ratio":0.30612244897959184,"type":"interior","recipe":[{"id":"Fragrant Cedar Wood","amount":12},{"id":"Red Dye","amount":6}]},"red_cedar_curio_stand":{"id":"red_cedar_curio_stand","name":"Red Cedar Curio Stand","load":201,"energy":60,"ratio":0.29850746268656714,"type":"interior","recipe":[{"id":"Fragrant Cedar Wood","amount":12},{"id":"Red Dye","amount":6}]},"shopkeepers_cedar_shelf":{"id":"shopkeepers_cedar_shelf","name":"Shopkeeper's Cedar Shelf","load":85,"energy":60,"ratio":0.7058823529411765,"type":"interior","recipe":[{"id":"Fragrant Cedar Wood","amount":12}]},"mondstadt_rug_crimson_ardor":{"id":"mondstadt_rug_crimson_ardor","name":"Mondstadt Rug: Crimson Ardor","load":85,"energy":60,"ratio":0.7058823529411765,"type":"interior","recipe":[{"id":"Fabric","amount":8},{"id":"Red Dye","amount":4}]},"mondstadt_rug_tireless_search":{"id":"mondstadt_rug_tireless_search","name":"Mondstadt Rug: Tireless Search","load":85,"energy":60,"ratio":0.7058823529411765,"type":"interior","recipe":[{"id":"Fabric","amount":8},{"id":"Blue Dye","amount":4}]},"tavern_rug_home_away_from_home":{"id":"tavern_rug_home_away_from_home","name":"Tavern Rug: Home Away From Home","load":85,"energy":60,"ratio":0.7058823529411765,"type":"interior","recipe":[{"id":"Fabric","amount":8},{"id":"Yellow Dye","amount":2},{"id":"Blue Dye","amount":2}]},"entrance_rug_a_warm_welcome":{"id":"entrance_rug_a_warm_welcome","name":"Entrance Rug: A Warm Welcome","load":85,"energy":60,"ratio":0.7058823529411765,"type":"interior","recipe":[{"id":"Fabric","amount":8},{"id":"Red Dye","amount":2},{"id":"Yellow Dye","amount":2}]},"rally_banner":{"id":"rally_banner","name":"Rally Banner","load":85,"energy":60,"ratio":0.7058823529411765,"type":"interior","recipe":[{"id":"Birch Wood","amount":4},{"id":"Fabric","amount":4},{"id":"Red Dye","amount":4}]},"pure_spirit_banner":{"id":"pure_spirit_banner","name":"Pure Spirit Banner","load":85,"energy":60,"ratio":0.7058823529411765,"type":"interior","recipe":[{"id":"Birch Wood","amount":4},{"id":"Fabric","amount":4},{"id":"Yellow Dye","amount":4}]},"neat_stack_of_books":{"id":"neat_stack_of_books","name":"Neat Stack of Books","load":85,"energy":60,"ratio":0.7058823529411765,"type":"interior","recipe":[{"id":"Pine Wood","amount":4},{"id":"Red Dye","amount":4}]},"scholars_weariness":{"id":"scholars_weariness","name":"\"Scholar's Weariness\"","load":85,"energy":60,"ratio":0.7058823529411765,"type":"interior","recipe":[{"id":"Pine Wood","amount":4},{"id":"Blue Dye","amount":4}]},"etiquette_of_correspondence":{"id":"etiquette_of_correspondence","name":"\"Etiquette of Correspondence\"","load":85,"energy":60,"ratio":0.7058823529411765,"type":"interior","recipe":[{"id":"Pine Wood","amount":4}]},"exquisite_hourglass_ornament":{"id":"exquisite_hourglass_ornament","name":"Exquisite Hourglass Ornament","load":169,"energy":60,"ratio":0.35502958579881655,"type":"interior","recipe":[{"id":"White Iron Chunk","amount":4},{"id":"Blue Dye","amount":4}]},"flower_arrangement_baby_blue_tranquility":{"id":"flower_arrangement_baby_blue_tranquility","name":"Flower Arrangement: Baby Blue Tranquility","load":169,"energy":60,"ratio":0.35502958579881655,"type":"interior","recipe":[{"id":"White Iron Chunk","amount":8}]},"potted_plant_crystalline_breeze":{"id":"potted_plant_crystalline_breeze","name":"Potted Plant: Crystalline Breeze","load":169,"energy":60,"ratio":0.35502958579881655,"type":"interior","recipe":[{"id":"White Iron Chunk","amount":4},{"id":"Blue Dye","amount":4}]},"flower_arrangement_sprawling_daybreak":{"id":"flower_arrangement_sprawling_daybreak","name":"Flower Arrangement: Sprawling Daybreak","load":169,"energy":60,"ratio":0.35502958579881655,"type":"interior","recipe":[{"id":"Pine Wood","amount":4},{"id":"Red Dye","amount":4}]},"potted_flower_fragrant_facade":{"id":"potted_flower_fragrant_facade","name":"Potted Flower: Fragrant Facade","load":169,"energy":60,"ratio":0.35502958579881655,"type":"interior","recipe":[{"id":"Pine Wood","amount":4},{"id":"Blue Dye","amount":4}]},"alchemic_device_between_fire_and_water":{"id":"alchemic_device_between_fire_and_water","name":"Alchemic Device: Between Fire and Water","load":169,"energy":60,"ratio":0.35502958579881655,"type":"interior","recipe":[{"id":"White Iron Chunk","amount":4},{"id":"Red Dye","amount":4}]},"alchemic_component_burden_of_dust":{"id":"alchemic_component_burden_of_dust","name":"Alchemic Component: Burden of Dust","load":113,"energy":60,"ratio":0.5309734513274337,"type":"interior","recipe":[{"id":"White Iron Chunk","amount":4},{"id":"Red Dye","amount":4}]},"calligraphy_set_assiduous_calligraphy":{"id":"calligraphy_set_assiduous_calligraphy","name":"Calligraphy Set: Assiduous Calligraphy","load":85,"energy":60,"ratio":0.7058823529411765,"type":"interior","recipe":[{"id":"Bamboo Segment","amount":4},{"id":"Blue Dye","amount":4},{"id":"White Iron Chunk","amount":4}]},"potted_plant_petite_perrenial":{"id":"potted_plant_petite_perrenial","name":"Potted Plant: Petite Perrenial","load":338,"energy":60,"ratio":0.17751479289940827,"type":"interior","recipe":[{"id":"Pine Wood","amount":4},{"id":"Blue Dye","amount":4}]},"golden_triple-arm_candelabrum":{"id":"golden_triple-arm_candelabrum","name":"Golden Triple-Arm Candelabrum","load":85,"energy":60,"ratio":0.7058823529411765,"type":"interior","recipe":[{"id":"Iron Chunk","amount":4},{"id":"Yellow Dye","amount":4}]},"breeze-blessed_bed":{"id":"breeze-blessed_bed","name":"Breeze-Blessed Bed","load":85,"energy":60,"ratio":0.7058823529411765,"type":"interior","recipe":[{"id":"Fragrant Cedar Wood","amount":12},{"id":"Blue Dye","amount":3},{"id":"Red Dye","amount":3}]},"cloudy_haze_bed":{"id":"cloudy_haze_bed","name":"Cloudy Haze Bed","load":85,"energy":60,"ratio":0.7058823529411765,"type":"interior","recipe":[{"id":"Sandbearer Wood","amount":12},{"id":"Yellow Dye","amount":3},{"id":"Red Dye","amount":3}]},"large_birch_wardrobe":{"id":"large_birch_wardrobe","name":"Large Birch Wardrobe","load":85,"energy":60,"ratio":0.7058823529411765,"type":"interior","recipe":[{"id":"Birch Wood","amount":12}]},"birch_double_drawer_nightstand":{"id":"birch_double_drawer_nightstand","name":"Birch Double Drawer Nightstand","load":85,"energy":60,"ratio":0.7058823529411765,"type":"interior","recipe":[{"id":"Birch Wood","amount":8}]},"gold-lined_sandbearer_nightstand":{"id":"gold-lined_sandbearer_nightstand","name":"Gold-Lined Sandbearer Nightstand","load":85,"energy":60,"ratio":0.7058823529411765,"type":"interior","recipe":[{"id":"Sandbearer Wood","amount":8},{"id":"Blue Dye","amount":2},{"id":"Red Dye","amount":2}]},"gold-lined_sandbearer_wardrobe":{"id":"gold-lined_sandbearer_wardrobe","name":"Gold-Lined Sandbearer Wardrobe","load":85,"energy":60,"ratio":0.7058823529411765,"type":"interior","recipe":[{"id":"Sandbearer Wood","amount":12},{"id":"Blue Dye","amount":3},{"id":"Red Dye","amount":3}]},"seashell_table_lamp":{"id":"seashell_table_lamp","name":"Seashell Table Lamp","load":85,"energy":60,"ratio":0.7058823529411765,"type":"interior","recipe":[{"id":"Iron Chunk","amount":8}]},"bustling_sundry_stand":{"id":"bustling_sundry_stand","name":"Bustling Sundry Stand","load":60,"energy":60,"ratio":1,"type":"exterior","recipe":[{"id":"Fir Wood","amount":8},{"id":"Fabric","amount":2},{"id":"Red Dye","amount":2}]},"profitable_fruit_stand":{"id":"profitable_fruit_stand","name":"Profitable Fruit Stand","load":145,"energy":60,"ratio":0.41379310344827586,"type":"exterior","recipe":[{"id":"Fir Wood","amount":8},{"id":"Fabric","amount":2},{"id":"Blue Dye","amount":2}]},"real_deal_fruit_stand":{"id":"real_deal_fruit_stand","name":"Real Deal Fruit Stand","load":175,"energy":60,"ratio":0.34285714285714286,"type":"exterior","recipe":[{"id":"Fir Wood","amount":8},{"id":"Fabric","amount":4}]},"bountiful_harvest_fruit_cart":{"id":"bountiful_harvest_fruit_cart","name":"Bountiful Harvest Fruit Cart","load":80,"energy":60,"ratio":0.75,"type":"exterior","recipe":[{"id":"Fir Wood","amount":4},{"id":"Fabric","amount":4},{"id":"Red Dye","amount":4}]},"multi-arched_mondstadt_building":{"id":"multi-arched_mondstadt_building","name":"Multi-Arched Mondstadt Building","load":205,"energy":60,"ratio":0.2926829268292683,"type":"exterior","recipe":[{"id":"Fir Wood","amount":12},{"id":"Birch Wood","amount":6}]},"mondstadt_house_with_overhanging_attic":{"id":"mondstadt_house_with_overhanging_attic","name":"Mondstadt House With Overhanging Attic","load":255,"energy":60,"ratio":0.23529411764705882,"type":"exterior","recipe":[{"id":"Fir Wood","amount":12},{"id":"Birch Wood","amount":6}]},"warm_and_dry_mondstadt_apartment":{"id":"warm_and_dry_mondstadt_apartment","name":"Warm and Dry Mondstadt Apartment","load":245,"energy":60,"ratio":0.24489795918367346,"type":"exterior","recipe":[{"id":"Fir Wood","amount":12},{"id":"Birch Wood","amount":6}]},"old_wind-resistant_mondstadt_house":{"id":"old_wind-resistant_mondstadt_house","name":"Old Wind-Resistant Mondstadt House","load":200,"energy":60,"ratio":0.3,"type":"exterior","recipe":[{"id":"Fir Wood","amount":12},{"id":"Birch Wood","amount":6}]},"country_home_with_tall_attic":{"id":"country_home_with_tall_attic","name":"Country Home With Tall Attic","load":300,"energy":60,"ratio":0.2,"type":"exterior","recipe":[{"id":"Fir Wood","amount":12},{"id":"Birch Wood","amount":6}]},"classic_country_home":{"id":"classic_country_home","name":"Classic Country Home","load":195,"energy":60,"ratio":0.3076923076923077,"type":"exterior","recipe":[{"id":"Fir Wood","amount":12},{"id":"Birch Wood","amount":6}]},"pocket-sized_pine_cabin":{"id":"pocket-sized_pine_cabin","name":"Pocket-Sized Pine Cabin","load":160,"energy":60,"ratio":0.375,"type":"exterior","recipe":[{"id":"Pine Wood","amount":12}]},"traveling_merchant_north_of_the_stone_gate":{"id":"traveling_merchant_north_of_the_stone_gate","name":"\"Traveling Merchant North of the Stone Gate\"","load":85,"energy":60,"ratio":0.7058823529411765,"type":"exterior","recipe":[{"id":"Bamboo Segment","amount":12}]},"clouds_east_of_bishui":{"id":"clouds_east_of_bishui","name":"\"Clouds East of Bishui\"","load":125,"energy":60,"ratio":0.48,"type":"exterior","recipe":[{"id":"Fir Wood","amount":8},{"id":"Fabric","amount":2},{"id":"Blue Dye","amount":2}]},"roll-roofed_fruit_and_vegetable_cart":{"id":"roll-roofed_fruit_and_vegetable_cart","name":"Roll-Roofed Fruit and Vegetable Cart","load":110,"energy":60,"ratio":0.5454545454545454,"type":"exterior","recipe":[{"id":"Birch Wood","amount":12}]},"liyue_house_solitary_retreat":{"id":"liyue_house_solitary_retreat","name":"Liyue House: Solitary Retreat","load":210,"energy":60,"ratio":0.2857142857142857,"type":"exterior","recipe":[{"id":"Pine Wood","amount":6},{"id":"Sandbearer Wood","amount":6},{"id":"White Iron Chunk","amount":6}]},"liyue_house_of_timber_and_stone":{"id":"liyue_house_of_timber_and_stone","name":"Liyue House: Of Timber and Stone","load":205,"energy":60,"ratio":0.2926829268292683,"type":"exterior","recipe":[{"id":"Pine Wood","amount":6},{"id":"Sandbearer Wood","amount":6},{"id":"White Iron Chunk","amount":6}]},"liyue_pitstop_tea_fragrance_on_the_old_road":{"id":"liyue_pitstop_tea_fragrance_on_the_old_road","name":"Liyue Pitstop: Tea Fragrance on the Old Road","load":185,"energy":60,"ratio":0.32432432432432434,"type":"exterior","recipe":[{"id":"Pine Wood","amount":6},{"id":"Sandbearer Wood","amount":6},{"id":"White Iron Chunk","amount":6}]},"liyue_house_moon-crested_eaves":{"id":"liyue_house_moon-crested_eaves","name":"Liyue House: Moon-Crested Eaves","load":85,"energy":60,"ratio":0.7058823529411765,"type":"exterior","recipe":[{"id":"Pine Wood","amount":6},{"id":"Sandbearer Wood","amount":6},{"id":"White Iron Chunk","amount":6}]},"liyue_house_amity_abounds":{"id":"liyue_house_amity_abounds","name":"Liyue House: Amity Abounds","load":85,"energy":60,"ratio":0.7058823529411765,"type":"exterior","recipe":[{"id":"Pine Wood","amount":6},{"id":"Sandbearer Wood","amount":6},{"id":"White Iron Chunk","amount":6}]},"liyue_shop_citywide_favorite":{"id":"liyue_shop_citywide_favorite","name":"Liyue Shop: Citywide Favorite","load":85,"energy":60,"ratio":0.7058823529411765,"type":"exterior","recipe":[{"id":"Pine Wood","amount":6},{"id":"Sandbearer Wood","amount":6},{"id":"White Iron Chunk","amount":6}]},"liyue_house_time_waits_for_no-one":{"id":"liyue_house_time_waits_for_no-one","name":"Liyue House: Time Waits for No-One","load":85,"energy":60,"ratio":0.7058823529411765,"type":"exterior","recipe":[{"id":"Pine Wood","amount":6},{"id":"Sandbearer Wood","amount":6},{"id":"White Iron Chunk","amount":6}]},"hilichurl_outpost_hut":{"id":"hilichurl_outpost_hut","name":"Hilichurl Outpost Hut","load":155,"energy":60,"ratio":0.3870967741935484,"type":"exterior","recipe":[{"id":"Birch Wood","amount":12}]},"hilichurl_spiral_watchtower":{"id":"hilichurl_spiral_watchtower","name":"Hilichurl Spiral Watchtower","load":85,"energy":60,"ratio":0.7058823529411765,"type":"exterior","recipe":[{"id":"Birch Wood","amount":12}]},"two-story_hilichurl_sentry_tower":{"id":"two-story_hilichurl_sentry_tower","name":"Two-Story Hilichurl Sentry Tower","load":95,"energy":60,"ratio":0.631578947368421,"type":"exterior","recipe":[{"id":"Birch Wood","amount":12}]},"lightning_protective_tent":{"id":"lightning_protective_tent","name":"Lightning Protective Tent","load":110,"energy":60,"ratio":0.5454545454545454,"type":"exterior","recipe":[{"id":"Birch Wood","amount":8},{"id":"Fabric","amount":4}]},"simple_single-person_tent":{"id":"simple_single-person_tent","name":"Simple Single-Person Tent","load":65,"energy":60,"ratio":0.9230769230769231,"type":"exterior","recipe":[{"id":"Birch Wood","amount":8},{"id":"Fabric","amount":4}]},"heavy_fir_forging_table":{"id":"heavy_fir_forging_table","name":"Heavy Fir Forging Table","load":35,"energy":60,"ratio":1.7142857142857142,"type":"exterior","recipe":[{"id":"Fir Wood","amount":12},{"id":"Fabric","amount":4}]},"four-quadrant_cooking_cauldron":{"id":"four-quadrant_cooking_cauldron","name":"\"Four-Quadrant Cooking Cauldron\"","load":145,"energy":60,"ratio":0.41379310344827586,"type":"exterior","recipe":[{"id":"Birch Wood","amount":8},{"id":"Fabric","amount":4}]},"large_stone_mill":{"id":"large_stone_mill","name":"Large Stone Mill","load":35,"energy":60,"ratio":1.7142857142857142,"type":"exterior","recipe":[{"id":"Fir Wood","amount":4},{"id":"Iron Chunk","amount":8}]},"hardwood_weapon_rack":{"id":"hardwood_weapon_rack","name":"Hardwood Weapon Rack","load":35,"energy":60,"ratio":1.7142857142857142,"type":"exterior","recipe":[{"id":"Fir Wood","amount":8}]},"sturdy_stone_well":{"id":"sturdy_stone_well","name":"Sturdy Stone Well","load":190,"energy":60,"ratio":0.3157894736842105,"type":"exterior","recipe":[{"id":"White Iron Chunk","amount":8},{"id":"Fir Wood","amount":4}]},"wine_jar_with_bamboo_casing_spirits_awaiting_moonrise":{"id":"wine_jar_with_bamboo_casing_spirits_awaiting_moonrise","name":"Wine Jar With Bamboo Casing: Spirits Awaiting Moonrise","load":65,"energy":60,"ratio":0.9230769230769231,"type":"exterior","recipe":[{"id":"Bamboo Segment","amount":12}]},"potted_plant_verdant_vastness":{"id":"potted_plant_verdant_vastness","name":"Potted Plant: Verdant Vastness","load":125,"energy":60,"ratio":0.48,"type":"exterior","recipe":[{"id":"White Iron Chunk","amount":4},{"id":"Pine Wood","amount":8}]},"toy_stand_dazzling_delights":{"id":"toy_stand_dazzling_delights","name":"Toy Stand: Dazzling Delights","load":85,"energy":60,"ratio":0.7058823529411765,"type":"exterior","recipe":[{"id":"Fir Wood","amount":4},{"id":"Bamboo Segment","amount":4},{"id":"Fabric","amount":4}]},"umbrella_shop_kaleidoscope_of_parasol_colors":{"id":"umbrella_shop_kaleidoscope_of_parasol_colors","name":"Umbrella Shop: Kaleidoscope of Parasol Colors","load":110,"energy":60,"ratio":0.5454545454545454,"type":"exterior","recipe":[{"id":"Fir Wood","amount":4},{"id":"Bamboo Segment","amount":4},{"id":"Fabric","amount":4}]},"fruit_and_veggie_stall_harvest_bounties":{"id":"fruit_and_veggie_stall_harvest_bounties","name":"Fruit and Veggie Stall: Harvest Bounties","load":60,"energy":60,"ratio":1,"type":"exterior","recipe":[{"id":"Pine Wood","amount":12}]},"wine_shop_display_counter_to_your_hearts_content":{"id":"wine_shop_display_counter_to_your_hearts_content","name":"Wine Shop Display Counter: To Your Heart's Content","load":65,"energy":60,"ratio":0.9230769230769231,"type":"exterior","recipe":[{"id":"Pine Wood","amount":12}]},"crude_double-decker_pallet":{"id":"crude_double-decker_pallet","name":"Crude Double-Decker Pallet","load":95,"energy":60,"ratio":0.631578947368421,"type":"exterior","recipe":[{"id":"Fir Wood","amount":8},{"id":"Fabric","amount":4},{"id":"Blue Dye","amount":4}]},"two-tier_vendors_booth_rising_fortunes":{"id":"two-tier_vendors_booth_rising_fortunes","name":"Two-Tier Vendor's Booth: Rising Fortunes","load":60,"energy":60,"ratio":1,"type":"exterior","recipe":[{"id":"Pine Wood","amount":12}]},"farmers_scarecrow":{"id":"farmers_scarecrow","name":"Farmer's Scarecrow","load":35,"energy":60,"ratio":1.7142857142857142,"type":"exterior","recipe":[{"id":"Fir Wood","amount":4},{"id":"Fabric","amount":4},{"id":"Red Dye","amount":4}]},"roofed_well_for_purity":{"id":"roofed_well_for_purity","name":"Roofed Well: For Purity","load":190,"energy":60,"ratio":0.3157894736842105,"type":"exterior","recipe":[{"id":"White Iron Chunk","amount":4},{"id":"Fir Wood","amount":8}]},"fruit_sellers_caution":{"id":"fruit_sellers_caution","name":"Fruit Seller's Caution","load":35,"energy":60,"ratio":1.7142857142857142,"type":"exterior","recipe":[{"id":"Fabric","amount":12}]},"fruit_sellers_toil":{"id":"fruit_sellers_toil","name":"Fruit Seller's Toil","load":35,"energy":60,"ratio":1.7142857142857142,"type":"exterior","recipe":[{"id":"Fabric","amount":12}]},"hilichurl_archery_target":{"id":"hilichurl_archery_target","name":"Hilichurl Archery Target","load":65,"energy":60,"ratio":0.9230769230769231,"type":"exterior","recipe":[{"id":"Fir Wood","amount":8}]},"hilichurl_horned_pot":{"id":"hilichurl_horned_pot","name":"Hilichurl Horned Pot","load":35,"energy":60,"ratio":1.7142857142857142,"type":"exterior","recipe":[{"id":"Iron Chunk","amount":12}]},"bamboo_outdoor_tea_table":{"id":"bamboo_outdoor_tea_table","name":"Bamboo Outdoor Tea Table","load":95,"energy":60,"ratio":0.631578947368421,"type":"exterior","recipe":[{"id":"Bamboo Segment","amount":12}]},"wooden_outdoor_tea_table":{"id":"wooden_outdoor_tea_table","name":"Wooden Outdoor Tea Table","load":95,"energy":60,"ratio":0.631578947368421,"type":"exterior","recipe":[{"id":"Fir Wood","amount":12}]},"water-retaining_flower_beds":{"id":"water-retaining_flower_beds","name":"Water-Retaining Flower Beds","load":65,"energy":60,"ratio":0.9230769230769231,"type":"exterior","recipe":[{"id":"Fir Wood","amount":12}]},"lush_grapevine":{"id":"lush_grapevine","name":"Lush Grapevine","load":65,"energy":60,"ratio":0.9230769230769231,"type":"exterior","recipe":[{"id":"Fir Wood","amount":12}]},"wrought_iron_carved_street_light":{"id":"wrought_iron_carved_street_light","name":"Wrought Iron Carved Street Light","load":115,"energy":60,"ratio":0.5217391304347826,"type":"exterior","recipe":[{"id":"Iron Chunk","amount":4},{"id":"Fabric","amount":4},{"id":"Blue Dye","amount":4}]},"evil-repelling_lantern_all-around_lighting":{"id":"evil-repelling_lantern_all-around_lighting","name":"Evil-Repelling Lantern: All-Around Lighting","load":135,"energy":60,"ratio":0.4444444444444444,"type":"exterior","recipe":[{"id":"Pine Wood","amount":4},{"id":"Bamboo Segment","amount":4}]},"four_corners_lantern_amity_from_afar":{"id":"four_corners_lantern_amity_from_afar","name":"Four Corners Lantern: Amity From Afar","load":85,"energy":60,"ratio":0.7058823529411765,"type":"exterior","recipe":[{"id":"Pine Wood","amount":4},{"id":"Bamboo Segment","amount":4}]},"shadow_lamp_painted_shadow":{"id":"shadow_lamp_painted_shadow","name":"Shadow Lamp: Painted Shadow","load":115,"energy":60,"ratio":0.5217391304347826,"type":"exterior","recipe":[{"id":"Sandbearer Wood","amount":4},{"id":"Bamboo Segment","amount":4}]},"fragrant_cedar_vegetable_rack":{"id":"fragrant_cedar_vegetable_rack","name":"Fragrant Cedar Vegetable Rack","load":70,"energy":20,"ratio":0.2857142857142857,"type":"exterior","recipe":[{"id":"Fragrant Cedar Wood","amount":10},{"id":"Red Dye","amount":5}],"cost":60},"blooming_hedge":{"id":"blooming_hedge","name":"Blooming Hedge","load":50,"energy":20,"ratio":0.4,"type":"exterior","recipe":[{"id":"Fragrant Cedar Wood","amount":10}],"cost":80},"ordinary_garden_hedge":{"id":"ordinary_garden_hedge","name":"Ordinary Garden Hedge","load":50,"energy":20,"ratio":0.4,"type":"exterior","recipe":[{"id":"Fragrant Cedar Wood","amount":10}],"cost":80},"concealing_leaves":{"id":"concealing_leaves","name":"\"Concealing Leaves\"","load":50,"energy":20,"ratio":0.4,"type":"exterior","recipe":[{"id":"Fragrant Cedar Wood","amount":10}],"cost":80},"green_fountain":{"id":"green_fountain","name":"\"Green Fountain\"","load":50,"energy":20,"ratio":0.4,"type":"exterior","recipe":[{"id":"Fragrant Cedar Wood","amount":10}],"cost":80},"kindletree":{"id":"kindletree","name":"\"Kindletree\"","load":50,"energy":20,"ratio":0.4,"type":"exterior","recipe":[{"id":"Fragrant Cedar Wood","amount":10}],"cost":80},"crystalflys_perch":{"id":"crystalflys_perch","name":"\"Crystalfly's Perch\"","load":50,"energy":20,"ratio":0.4,"type":"exterior","recipe":[{"id":"Fragrant Cedar Wood","amount":10}],"cost":80},"southern_sweetleaves":{"id":"southern_sweetleaves","name":"\"Southern Sweetleaves\"","load":50,"energy":20,"ratio":0.4,"type":"exterior","recipe":[{"id":"Fragrant Cedar Wood","amount":10}],"cost":80},"brightcrown_plumebush":{"id":"brightcrown_plumebush","name":"\"Brightcrown Plumebush\"","load":50,"energy":20,"ratio":0.4,"type":"exterior","recipe":[{"id":"Fragrant Cedar Wood","amount":10}],"cost":80},"the_color_of_the_wind":{"id":"the_color_of_the_wind","name":"\"The Color of the Wind\"","load":150,"energy":20,"ratio":0.13333333333333333,"type":"exterior","recipe":[{"id":"Fragrant Cedar Wood","amount":20}],"cost":80},"silversand_coconut_tree":{"id":"silversand_coconut_tree","name":"Silversand Coconut Tree","load":50,"energy":20,"ratio":0.4,"type":"exterior","recipe":[{"id":"Fragrant Cedar Wood","amount":20}],"cost":80},"whitesand_coconut_tree":{"id":"whitesand_coconut_tree","name":"Whitesand Coconut Tree","load":50,"energy":20,"ratio":0.4,"type":"exterior","recipe":[{"id":"Fragrant Cedar Wood","amount":20}],"cost":80},"tianheng_red_maple_branches_aflame":{"id":"tianheng_red_maple_branches_aflame","name":"Tianheng Red Maple: Branches Aflame","load":350,"energy":20,"ratio":0.05714285714285714,"type":"exterior","recipe":[{"id":"Fragrant Cedar Wood","amount":20}],"cost":80},"peculiar_knotwood_tree":{"id":"peculiar_knotwood_tree","name":"Peculiar Knotwood Tree","load":50,"energy":20,"ratio":0.4,"type":"exterior","recipe":[{"id":"Fragrant Cedar Wood","amount":20}],"cost":80},"yellow_sandbearer_tree":{"id":"yellow_sandbearer_tree","name":"Yellow Sandbearer Tree","load":100,"energy":20,"ratio":0.2,"type":"exterior","recipe":[{"id":"Fragrant Cedar Wood","amount":20}],"cost":80},"hiding_grazestone":{"id":"hiding_grazestone","name":"Hiding Grazestone","load":35,"energy":20,"ratio":0.5714285714285714,"type":"exterior","recipe":[{"id":"White Iron Chunk","amount":10}],"cost":80},"recreation_stone":{"id":"recreation_stone","name":"Recreation Stone","load":35,"energy":20,"ratio":0.5714285714285714,"type":"exterior","recipe":[{"id":"White Iron Chunk","amount":10}],"cost":80},"unmoving_kingstone":{"id":"unmoving_kingstone","name":"Unmoving Kingstone","load":35,"energy":20,"ratio":0.5714285714285714,"type":"exterior","recipe":[{"id":"White Iron Chunk","amount":10}],"cost":80},"the_adventurers_burdens":{"id":"the_adventurers_burdens","name":"\"The Adventurer's Burdens\"","load":35,"energy":60,"ratio":1.7142857142857142,"type":"exterior","recipe":[{"id":"Fabric","amount":4},{"id":"Pine Wood","amount":4}]},"mature_cuihua_tree":{"id":"mature_cuihua_tree","name":"Mature Cuihua Tree","load":200,"energy":20,"ratio":0.1,"type":"exterior","cost":80},"cuihua_sapling":{"id":"cuihua_sapling","name":"Cuihua Sapling","load":100,"energy":20,"ratio":0.2,"type":"exterior","cost":80},"tall_birch":{"id":"tall_birch","name":"Tall Birch","load":250,"energy":20,"ratio":0.08,"type":"exterior","cost":80},"birch_sapling":{"id":"birch_sapling","name":"Birch Sapling","load":250,"energy":20,"ratio":0.08,"type":"exterior","cost":80},"golden_knotwood_tree":{"id":"golden_knotwood_tree","name":"Golden Knotwood Tree","load":200,"energy":20,"ratio":0.1,"type":"exterior","cost":80},"green_knotwood_tree":{"id":"green_knotwood_tree","name":"Green Knotwood Tree","load":100,"energy":20,"ratio":0.2,"type":"exterior","cost":80},"amber_knotwood_tree":{"id":"amber_knotwood_tree","name":"Amber Knotwood Tree","load":100,"energy":20,"ratio":0.2,"type":"exterior","cost":80},"amber_irontrunk_tree":{"id":"amber_irontrunk_tree","name":"Amber Irontrunk Tree","load":100,"energy":20,"ratio":0.2,"type":"exterior","cost":80},"golden_irontrunk_tree":{"id":"golden_irontrunk_tree","name":"Golden Irontrunk Tree","load":100,"energy":20,"ratio":0.2,"type":"exterior","cost":80},"green_irontrunk_tree":{"id":"green_irontrunk_tree","name":"Green Irontrunk Tree","load":100,"energy":20,"ratio":0.2,"type":"exterior","cost":80},"qingce_heronleaf_bamboo":{"id":"qingce_heronleaf_bamboo","name":"Qingce Heronleaf Bamboo","load":50,"energy":20,"ratio":0.4,"type":"exterior","cost":80},"qingce_skysail_bamboo":{"id":"qingce_skysail_bamboo","name":"Qingce Skysail Bamboo","load":100,"energy":20,"ratio":0.2,"type":"exterior","cost":80},"qingce_jadestone_bamboo":{"id":"qingce_jadestone_bamboo","name":"Qingce Jadestone Bamboo","load":50,"energy":20,"ratio":0.4,"type":"exterior","cost":80},"verdurous_feast":{"id":"verdurous_feast","name":"Verdurous Feast","load":50,"energy":20,"ratio":0.4,"type":"exterior","cost":80},"verdurous_waiter":{"id":"verdurous_waiter","name":"Verdurous Waiter","load":50,"energy":20,"ratio":0.4,"type":"exterior","cost":80},"golden_pearlroot_tree":{"id":"golden_pearlroot_tree","name":"Golden Pearlroot Tree","load":50,"energy":20,"ratio":0.4,"type":"exterior","cost":80},"amber_pearlroot_tree":{"id":"amber_pearlroot_tree","name":"Amber Pearlroot Tree","load":50,"energy":20,"ratio":0.4,"type":"exterior","cost":80},"withered_pearlroot_tree":{"id":"withered_pearlroot_tree","name":"Withered Pearlroot Tree","load":50,"energy":20,"ratio":0.4,"type":"exterior","cost":80},"green_pearlroot_tree":{"id":"green_pearlroot_tree","name":"Green Pearlroot Tree","load":50,"energy":20,"ratio":0.4,"type":"exterior","cost":80},"a_seat_in_the_wilderness":{"id":"a_seat_in_the_wilderness","name":"\"A Seat in the Wilderness\"","load":50,"energy":20,"ratio":0.4,"type":"exterior","cost":80},"hunters_vantage":{"id":"hunters_vantage","name":"\"Hunter's Vantage\"","load":50,"energy":20,"ratio":0.4,"type":"exterior","cost":80},"preys_cloak_of_refuge":{"id":"preys_cloak_of_refuge","name":"\"Prey's Cloak of Refuge\"","load":50,"energy":20,"ratio":0.4,"type":"exterior","cost":80},"moonlight_stone":{"id":"moonlight_stone","name":"Moonlight Stone","load":35,"energy":20,"ratio":0.5714285714285714,"type":"exterior","cost":80},"sunset_stone":{"id":"sunset_stone","name":"Sunset Stone","load":35,"energy":20,"ratio":0.5714285714285714,"type":"exterior","cost":80},"scorched_stone":{"id":"scorched_stone","name":"Scorched Stone","load":35,"energy":20,"ratio":0.5714285714285714,"type":"exterior","cost":80},"goldchime_stone":{"id":"goldchime_stone","name":"Goldchime Stone","load":35,"energy":20,"ratio":0.5714285714285714,"type":"exterior","cost":80},"goldbud_stone":{"id":"goldbud_stone","name":"Goldbud Stone","load":35,"energy":20,"ratio":0.5714285714285714,"type":"exterior","cost":80},"summer_solstice_rock":{"id":"summer_solstice_rock","name":"Summer Solstice Rock","load":35,"energy":20,"ratio":0.5714285714285714,"type":"exterior","cost":80},"formation_rock":{"id":"formation_rock","name":"Formation Rock","load":35,"energy":20,"ratio":0.5714285714285714,"type":"exterior","cost":80},"dainty_fists":{"id":"dainty_fists","name":"\"Dainty Fists\"","load":35,"energy":20,"ratio":0.5714285714285714,"type":"exterior","cost":80},"chasms_doorstep":{"id":"chasms_doorstep","name":"Chasm's Doorstep","load":35,"energy":20,"ratio":0.5714285714285714,"type":"exterior","cost":80},"parched_stone":{"id":"parched_stone","name":"Parched Stone","load":35,"energy":20,"ratio":0.5714285714285714,"type":"exterior","cost":80},"ashen_stone":{"id":"ashen_stone","name":"Ashen Stone","load":35,"energy":20,"ratio":0.5714285714285714,"type":"exterior","cost":80},"sartorial_stone":{"id":"sartorial_stone","name":"Sartorial Stone","load":35,"energy":20,"ratio":0.5714285714285714,"type":"exterior","cost":80},"moss-covered_stone":{"id":"moss-covered_stone","name":"Moss-Covered Stone","load":35,"energy":20,"ratio":0.5714285714285714,"type":"exterior","cost":80},"stratus-cloud_stone":{"id":"stratus-cloud_stone","name":"Stratus-Cloud Stone","load":35,"energy":20,"ratio":0.5714285714285714,"type":"exterior","cost":80},"stepping_stone":{"id":"stepping_stone","name":"Stepping Stone","load":35,"energy":20,"ratio":0.5714285714285714,"type":"exterior","cost":80},"unprecedentedly_average_stone":{"id":"unprecedentedly_average_stone","name":"Unprecedentedly Average Stone","load":35,"energy":20,"ratio":0.5714285714285714,"type":"exterior","cost":80},"embroidered_lantern_lofty_grandeur":{"id":"embroidered_lantern_lofty_grandeur","name":"Embroidered Lantern: Lofty Grandeur","load":220,"energy":90,"ratio":0.4090909090909091,"type":"interior","recipe":[{"id":"Sandbearer Wood","amount":12},{"id":"Fabric","amount":3},{"id":"Red Dye","amount":3}]},"wide_stone_stove":{"id":"wide_stone_stove","name":"Wide Stone Stove","load":558,"energy":90,"ratio":0.16129032258064516,"type":"interior","recipe":[{"id":"Iron Chunk","amount":4},{"id":"White Iron Chunk","amount":4}]},"pine_folding_screen_billowing_sails":{"id":"pine_folding_screen_billowing_sails","name":"Pine Folding Screen: Billowing Sails","load":85,"energy":90,"ratio":1.0588235294117647,"type":"interior","recipe":[{"id":"Pine Wood","amount":12},{"id":"Fabric","amount":3},{"id":"Red Dye","amount":3}]},"hardwood_screen_morning_mist_in_jueyun":{"id":"hardwood_screen_morning_mist_in_jueyun","name":"Hardwood Screen: Morning Mist in Jueyun","load":254,"energy":90,"ratio":0.3543307086614173,"type":"interior","recipe":[{"id":"Fragrant Cedar Wood","amount":12},{"id":"Fabric","amount":6}]},"soft_lounge_sofa":{"id":"soft_lounge_sofa","name":"Soft Lounge Sofa","load":169,"energy":90,"ratio":0.5325443786982249,"type":"interior","recipe":[{"id":"Pine Wood","amount":12},{"id":"Fabric","amount":6}]},"two-tier_library_bookshelf":{"id":"two-tier_library_bookshelf","name":"Two-Tier Library Bookshelf","load":254,"energy":90,"ratio":0.3543307086614173,"type":"interior","recipe":[{"id":"Cuihua Wood","amount":16},{"id":"Red Dye","amount":8}]},"exquisite_cuihua_bookshelf":{"id":"exquisite_cuihua_bookshelf","name":"Exquisite Cuihua Bookshelf","load":169,"energy":90,"ratio":0.5325443786982249,"type":"interior","recipe":[{"id":"Cuihua Wood","amount":16},{"id":"Red Dye","amount":8}]},"economy_cuihua_bookshelf":{"id":"economy_cuihua_bookshelf","name":"Economy Cuihua Bookshelf","load":169,"energy":90,"ratio":0.5325443786982249,"type":"interior","recipe":[{"id":"Cuihua Wood","amount":16},{"id":"Red Dye","amount":8}]},"lost_between_the_pages_of_a_book":{"id":"lost_between_the_pages_of_a_book","name":"\"Lost Between the Pages of a Book\"","load":270,"energy":90,"ratio":0.3333333333333333,"type":"interior","recipe":[{"id":"Birch Wood","amount":16},{"id":"Blue Dye","amount":4},{"id":"Red Dye","amount":4}]},"archivists_treasure_trove":{"id":"archivists_treasure_trove","name":"\"Archivist's Treasure Trove\"","load":169,"energy":90,"ratio":0.5325443786982249,"type":"interior","recipe":[{"id":"Birch Wood","amount":16},{"id":"Red Dye","amount":8}]},"landscape_painting_country_home":{"id":"landscape_painting_country_home","name":"Landscape Painting: Country Home","load":85,"energy":90,"ratio":1.0588235294117647,"type":"interior","recipe":[{"id":"Pine Wood","amount":8},{"id":"Blue Dye","amount":8},{"id":"Yellow Dye","amount":8}]},"landscape_painting_distant_clouds":{"id":"landscape_painting_distant_clouds","name":"Landscape Painting: Distant Clouds","load":85,"energy":90,"ratio":1.0588235294117647,"type":"interior","recipe":[{"id":"Pine Wood","amount":8},{"id":"Blue Dye","amount":8},{"id":"Yellow Dye","amount":8}]},"landscape_painting_nameless_precipice":{"id":"landscape_painting_nameless_precipice","name":"Landscape Painting: Nameless Precipice","load":85,"energy":90,"ratio":1.0588235294117647,"type":"interior","recipe":[{"id":"Pine Wood","amount":8},{"id":"Yellow Dye","amount":8},{"id":"Red Dye","amount":8}]},"favonius_coat_of_arms":{"id":"favonius_coat_of_arms","name":"Favonius Coat of Arms","load":85,"energy":90,"ratio":1.0588235294117647,"type":"interior","recipe":[{"id":"White Iron Chunk","amount":12},{"id":"Blue Dye","amount":6},{"id":"Yellow Dye","amount":6}]},"fine_brushwork_peaks_of_minlin":{"id":"fine_brushwork_peaks_of_minlin","name":"Fine Brushwork: Peaks of Minlin","load":85,"energy":90,"ratio":1.0588235294117647,"type":"interior","recipe":[{"id":"Bamboo Segment","amount":8},{"id":"Blue Dye","amount":8},{"id":"Yellow Dye","amount":8}]},"fine_brushwork_bowl_of_blossoms":{"id":"fine_brushwork_bowl_of_blossoms","name":"Fine Brushwork: Bowl of Blossoms","load":85,"energy":90,"ratio":1.0588235294117647,"type":"interior","recipe":[{"id":"Bamboo Segment","amount":8},{"id":"Blue Dye","amount":8},{"id":"Red Dye","amount":8}]},"fine_brushwork_mountains_rising_from_the_mist":{"id":"fine_brushwork_mountains_rising_from_the_mist","name":"Fine Brushwork: Mountains Rising From the Mist","load":85,"energy":90,"ratio":1.0588235294117647,"type":"interior","recipe":[{"id":"Bamboo Segment","amount":8},{"id":"Blue Dye","amount":8},{"id":"Yellow Dye","amount":8}]},"embroidered_curtains":{"id":"embroidered_curtains","name":"Embroidered Curtains","load":85,"energy":90,"ratio":1.0588235294117647,"type":"interior","recipe":[{"id":"Fabric","amount":12},{"id":"Red Dye","amount":12}]},"silk_curtains_fetching_the_sanguine_sky":{"id":"silk_curtains_fetching_the_sanguine_sky","name":"Silk Curtains: Fetching the Sanguine Sky","load":85,"energy":90,"ratio":1.0588235294117647,"type":"interior","recipe":[{"id":"Fabric","amount":12},{"id":"Yellow Dye","amount":6},{"id":"Red Dye","amount":6}]},"floral_screen_jade_and_gold":{"id":"floral_screen_jade_and_gold","name":"Floral Screen: Jade and Gold","load":85,"energy":90,"ratio":1.0588235294117647,"type":"interior","recipe":[{"id":"Fabric","amount":12},{"id":"Yellow Dye","amount":6},{"id":"Red Dye","amount":6}]},"open-air_workshop":{"id":"open-air_workshop","name":"Open-Air Workshop","load":190,"energy":90,"ratio":0.47368421052631576,"type":"exterior","recipe":[{"id":"Fir Wood","amount":12},{"id":"Iron Chunk","amount":6},{"id":"White Iron Chunk","amount":6}]},"bird_and_blossom_design_fountain":{"id":"bird_and_blossom_design_fountain","name":"Bird and Blossom Design Fountain","load":160,"energy":90,"ratio":0.5625,"type":"exterior","recipe":[{"id":"White Iron Chunk","amount":12},{"id":"Iron Chunk","amount":12}]},"adeptus_gate":{"id":"adeptus_gate","name":"Adeptus Gate","load":95,"energy":90,"ratio":0.9473684210526315,"type":"exterior","recipe":[{"id":"Pine Wood","amount":8},{"id":"Sandbearer Wood","amount":8},{"id":"White Iron Chunk","amount":8}]},"hilichurl_chieftain_hall":{"id":"hilichurl_chieftain_hall","name":"Hilichurl Chieftain Hall","load":290,"energy":90,"ratio":0.3103448275862069,"type":"exterior","recipe":[{"id":"Birch Wood","amount":30}]},"alchemists_crafting_bench":{"id":"alchemists_crafting_bench","name":"Alchemist's Crafting Bench","load":35,"energy":90,"ratio":2.5714285714285716,"type":"exterior","recipe":[{"id":"White Iron Chunk","amount":20}]},"stone_lion_statue_the_warding":{"id":"stone_lion_statue_the_warding","name":"Stone Lion Statue: The Warding","load":50,"energy":90,"ratio":1.8,"type":"exterior","recipe":[{"id":"White Iron Chunk","amount":12}]},"stone_lion_statue_the_knowing":{"id":"stone_lion_statue_the_knowing","name":"Stone Lion Statue: The Knowing","load":50,"energy":90,"ratio":1.8,"type":"exterior","recipe":[{"id":"White Iron Chunk","amount":12}]},"birch_main_courtyard_gate":{"id":"birch_main_courtyard_gate","name":"Birch Main Courtyard Gate","load":45,"energy":90,"ratio":2,"type":"exterior","recipe":[{"id":"Birch Wood","amount":12},{"id":"White Iron Chunk","amount":6}]},"carved_courtyard_fence_ending":{"id":"carved_courtyard_fence_ending","name":"Carved Courtyard Fence Ending","load":35,"energy":90,"ratio":2.5714285714285716,"type":"exterior","recipe":[{"id":"Birch Wood","amount":8},{"id":"White Iron Chunk","amount":4}]},"carved_courtyard_fence":{"id":"carved_courtyard_fence","name":"Carved Courtyard Fence","load":35,"energy":90,"ratio":2.5714285714285716,"type":"exterior","recipe":[{"id":"Birch Wood","amount":8},{"id":"White Iron Chunk","amount":4}]},"thundering_heavens_drum":{"id":"thundering_heavens_drum","name":"Thundering Heavens Drum","load":85,"energy":90,"ratio":1.0588235294117647,"type":"interior","recipe":[{"id":"Sandbearer Wood","amount":12},{"id":"Fabric","amount":6},{"id":"Yellow Dye","amount":6}]},"wing_house_dawn_&_dusk":{"id":"wing_house_dawn_&_dusk","name":"Wing House: Dawn & Dusk","load":185,"energy":90,"ratio":0.4864864864864865,"type":"exterior","recipe":[{"id":"Sandbearer Wood","amount":12},{"id":"Pine Wood","amount":12},{"id":"White Iron Chunk","amount":6}]},"pavilion_stargazers_shelter":{"id":"pavilion_stargazers_shelter","name":"Pavilion: Stargazer's Shelter","load":185,"energy":90,"ratio":0.4864864864864865,"type":"exterior","recipe":[{"id":"Sandbearer Wood","amount":18},{"id":"White Iron Chunk","amount":6}]},"scenic_corridor_sylvan_stroll":{"id":"scenic_corridor_sylvan_stroll","name":"Scenic Corridor: Sylvan Stroll","load":160,"energy":90,"ratio":0.5625,"type":"exterior","recipe":[{"id":"Sandbearer Wood","amount":12},{"id":"White Iron Chunk","amount":6}]},"courtyard_wall_spring_and_autumn_splendor":{"id":"courtyard_wall_spring_and_autumn_splendor","name":"Courtyard Wall: Spring and Autumn Splendor","load":95,"energy":90,"ratio":0.9473684210526315,"type":"exterior","recipe":[{"id":"Sandbearer Wood","amount":8},{"id":"White Iron Chunk","amount":4}]},"wall_corner_fragrant_nook":{"id":"wall_corner_fragrant_nook","name":"Wall Corner: Fragrant Nook","load":95,"energy":90,"ratio":0.9473684210526315,"type":"exterior","recipe":[{"id":"Sandbearer Wood","amount":8},{"id":"White Iron Chunk","amount":4}]},"courtyard_wall_all_in_a_row":{"id":"courtyard_wall_all_in_a_row","name":"Courtyard Wall: All in a Row","load":95,"energy":90,"ratio":0.9473684210526315,"type":"exterior","recipe":[{"id":"Sandbearer Wood","amount":8},{"id":"White Iron Chunk","amount":4}]},"courtyard_wall_peace_across":{"id":"courtyard_wall_peace_across","name":"Courtyard Wall: Peace Across","load":95,"energy":90,"ratio":0.9473684210526315,"type":"exterior","recipe":[{"id":"Sandbearer Wood","amount":8},{"id":"White Iron Chunk","amount":4}]},"main_entrance_gateway_to_the_clouds":{"id":"main_entrance_gateway_to_the_clouds","name":"Main Entrance: Gateway to the Clouds","load":180,"energy":90,"ratio":0.5,"type":"exterior","recipe":[{"id":"Sandbearer Wood","amount":12},{"id":"White Iron Chunk","amount":6}]},"perimeter_wall_scenic_archway":{"id":"perimeter_wall_scenic_archway","name":"Perimeter Wall: Scenic Archway","load":95,"energy":90,"ratio":0.9473684210526315,"type":"exterior","recipe":[{"id":"Sandbearer Wood","amount":12},{"id":"White Iron Chunk","amount":6}]},"adeptus_amber_a_striking_sight":{"id":"adeptus_amber_a_striking_sight","name":"Adeptus Amber: A Striking Sight","load":35,"energy":30,"ratio":0.8571428571428571,"type":"exterior","cost":120},"adeptus_amber_trespassers_beware":{"id":"adeptus_amber_trespassers_beware","name":"Adeptus Amber: Trespassers Beware","load":35,"energy":30,"ratio":0.8571428571428571,"type":"exterior","cost":120},"ballad-spinning_windwheel":{"id":"ballad-spinning_windwheel","name":"\"Ballad-Spinning Windwheel\"","load":185,"energy":90,"ratio":0.4864864864864865,"type":"exterior","recipe":[{"id":"Birch Wood","amount":24},{"id":"White Iron Chunk","amount":6}]},"tasseled_lantern_deck_the_streets":{"id":"tasseled_lantern_deck_the_streets","name":"Tasseled Lantern: Deck the Streets","load":305,"energy":90,"ratio":0.29508196721311475,"type":"interior","recipe":[{"id":"Sandbearer Wood","amount":6},{"id":"Fabric","amount":6},{"id":"Red Dye","amount":6}]},"lantern-lit_stage_crescendo":{"id":"lantern-lit_stage_crescendo","name":"Lantern-Lit Stage: Crescendo","load":175,"energy":90,"ratio":0.5142857142857142,"type":"interior","recipe":[{"id":"Fragrant Cedar Wood","amount":6},{"id":"Sandbearer Wood","amount":6},{"id":"Red Dye","amount":6}]},"mondstadt_mansion_windward_manor":{"id":"mondstadt_mansion_windward_manor","name":"Mondstadt Mansion: Windward Manor","load":945,"energy":750,"ratio":0.7936507936507936,"type":"exterior","recipe":[{"id":"Cuihua Wood","amount":50},{"id":"Yellow Dye","amount":20}]},"liyue_estate_exquisite_mansion":{"id":"liyue_estate_exquisite_mansion","name":"Liyue Estate: Exquisite Mansion","load":1440,"energy":750,"ratio":0.5208333333333334,"type":"exterior"}}